{
    "compos": [
        {
            "id": 0,
            "class": "EditText",
            "height": 48,
            "width": 900,
            "position": {
                "x1": 482,
                "y1": 118,
                "x2": 1382,
                "y2": 166
            },
            "children": [
                23
            ],
            "negative_template": false,
            "is_custom": false,
            "is_vism": false
        },
        {
            "id": 1,
            "class": "Icon-Info",
            "height": 30,
            "width": 30,
            "position": {
                "x1": 1649,
                "y1": 124,
                "x2": 1679,
                "y2": 154
            },
            "negative_template": false,
            "is_custom": false,
            "is_vism": false
        },
        {
            "id": 2,
            "class": "Icon-Edit",
            "height": 9,
            "width": 9,
            "position": {
                "x1": 1724,
                "y1": 124,
                "x2": 1733,
                "y2": 133
            },
            "negative_template": false,
            "is_custom": false,
            "is_vism": false
        },
        {
            "id": 3,
            "class": "RadioButton",
            "height": 36,
            "width": 36,
            "position": {
                "x1": 1751,
                "y1": 124,
                "x2": 1787,
                "y2": 160
            },
            "negative_template": false,
            "is_custom": false,
            "is_vism": false
        },
        {
            "id": 4,
            "class": "Icon-Notification",
            "height": 24,
            "width": 24,
            "position": {
                "x1": 1703,
                "y1": 130,
                "x2": 1727,
                "y2": 154
            },
            "negative_template": false,
            "is_custom": false,
            "is_vism": false
        },
        {
            "id": 5,
            "class": "Icon-Previous",
            "height": 24,
            "width": 24,
            "position": {
                "x1": 1867,
                "y1": 204,
                "x2": 1891,
                "y2": 228
            },
            "negative_template": false,
            "is_custom": false,
            "is_vism": false
        },
        {
            "id": 6,
            "class": "Button",
            "height": 48,
            "width": 166,
            "position": {
                "x1": 388,
                "y1": 250,
                "x2": 554,
                "y2": 298
            },
            "children": [
                28
            ],
            "negative_template": false,
            "is_custom": false,
            "is_vism": false
        },
        {
            "id": 7,
            "class": "RadioButton",
            "height": 48,
            "width": 163,
            "position": {
                "x1": 578,
                "y1": 250,
                "x2": 741,
                "y2": 298
            },
            "children": [
                29
            ],
            "negative_template": false,
            "is_custom": false,
            "is_vism": false
        },
        {
            "id": 8,
            "class": "Button",
            "height": 48,
            "width": 187,
            "position": {
                "x1": 790,
                "y1": 250,
                "x2": 977,
                "y2": 298
            },
            "children": [
                30
            ],
            "negative_template": false,
            "is_custom": false,
            "is_vism": false
        },
        {
            "id": 9,
            "class": "Icon-Notification",
            "height": 48,
            "width": 48,
            "position": {
                "x1": 989,
                "y1": 250,
                "x2": 1037,
                "y2": 298
            },
            "negative_template": false,
            "is_custom": false,
            "is_vism": false
        },
        {
            "id": 10,
            "class": "Icon-Link",
            "height": 48,
            "width": 48,
            "position": {
                "x1": 1331,
                "y1": 250,
                "x2": 1379,
                "y2": 298
            },
            "negative_template": false,
            "is_custom": false,
            "is_vism": false
        },
        {
            "id": 11,
            "class": "Checkbox",
            "height": 48,
            "width": 130,
            "position": {
                "x1": 1391,
                "y1": 250,
                "x2": 1521,
                "y2": 298
            },
            "children": [
                31
            ],
            "checkbox_state": "checked",
            "negative_template": false,
            "is_custom": false,
            "is_vism": false
        },
        {
            "id": 12,
            "class": "Icon-Checkmark",
            "height": 48,
            "width": 48,
            "position": {
                "x1": 1523,
                "y1": 250,
                "x2": 1571,
                "y2": 298
            },
            "negative_template": false,
            "is_custom": false,
            "is_vism": false
        },
        {
            "id": 13,
            "class": "Icon-Info",
            "height": 24,
            "width": 24,
            "position": {
                "x1": 1867,
                "y1": 301,
                "x2": 1891,
                "y2": 325
            },
            "negative_template": false,
            "is_custom": false,
            "is_vism": false
        },
        {
            "id": 14,
            "class": "Button",
            "height": 19,
            "width": 23,
            "position": {
                "x1": 70,
                "y1": 328,
                "x2": 93,
                "y2": 347
            },
            "negative_template": false,
            "is_custom": false,
            "is_vism": false
        },
        {
            "id": 15,
            "class": "Icon-Next",
            "height": 24,
            "width": 24,
            "position": {
                "x1": 1867,
                "y1": 373,
                "x2": 1891,
                "y2": 397
            },
            "negative_template": false,
            "is_custom": false,
            "is_vism": false
        },
        {
            "id": 16,
            "class": "Icon-Time",
            "height": 23,
            "width": 27,
            "position": {
                "x1": 1866,
                "y1": 445,
                "x2": 1893,
                "y2": 468
            },
            "negative_template": false,
            "is_custom": false,
            "is_vism": false
        },
        {
            "id": 17,
            "class": "Icon-Upload",
            "height": 67,
            "width": 76,
            "position": {
                "x1": 1038,
                "y1": 563,
                "x2": 1114,
                "y2": 630
            },
            "negative_template": false,
            "is_custom": false,
            "is_vism": false
        },
        {
            "id": 18,
            "class": "Button",
            "height": 60,
            "width": 499,
            "position": {
                "x1": 827,
                "y1": 902,
                "x2": 1326,
                "y2": 962
            },
            "children": [
                44
            ],
            "negative_template": false,
            "is_custom": false,
            "is_vism": false
        },
        {
            "id": 19,
            "class": "Button",
            "height": 9,
            "width": 264,
            "position": {
                "x1": 52,
                "y1": 916,
                "x2": 316,
                "y2": 925
            },
            "negative_template": false,
            "is_custom": false,
            "is_vism": false
        },
        {
            "id": 20,
            "class": "Button",
            "height": 60,
            "width": 499,
            "position": {
                "x1": 827,
                "y1": 986,
                "x2": 1326,
                "y2": 1046
            },
            "children": [
                46
            ],
            "negative_template": false,
            "is_custom": false,
            "is_vism": false
        },
        {
            "id": 21,
            "class": "Text",
            "height": 28,
            "width": 32,
            "position": {
                "x1": 26,
                "y1": 127,
                "x2": 58,
                "y2": 155
            },
            "text_content": ":::",
            "negative_template": false,
            "is_custom": false,
            "is_vism": false
        },
        {
            "id": 22,
            "class": "Text",
            "height": 28,
            "width": 152,
            "position": {
                "x1": 70,
                "y1": 127,
                "x2": 222,
                "y2": 155
            },
            "text_content": "Dropbox",
            "negative_template": false,
            "is_custom": false,
            "is_vism": false
        },
        {
            "id": 23,
            "class": "Text",
            "height": 28,
            "width": 106,
            "position": {
                "x1": 498,
                "y1": 129,
                "x2": 604,
                "y2": 157
            },
            "text_content": "Q Search",
            "parent": 0,
            "negative_template": false,
            "is_custom": false,
            "is_vism": false
        },
        {
            "id": 24,
            "class": "Text",
            "height": 28,
            "width": 92,
            "position": {
                "x1": 1808,
                "y1": 129,
                "x2": 1900,
                "y2": 157
            },
            "text_content": "Upgrade",
            "negative_template": false,
            "is_custom": false,
            "is_vism": false
        },
        {
            "id": 25,
            "class": "Text",
            "height": 30,
            "width": 240,
            "position": {
                "x1": 386,
                "y1": 200,
                "x2": 626,
                "y2": 230
            },
            "text_content": "Dropbox / Content",
            "negative_template": false,
            "is_custom": false,
            "is_vism": false
        },
        {
            "id": 26,
            "class": "Text",
            "height": 29,
            "width": 56,
            "position": {
                "x1": 1726,
                "y1": 201,
                "x2": 1782,
                "y2": 230
            },
            "text_content": "E v",
            "negative_template": false,
            "is_custom": false,
            "is_vism": false
        },
        {
            "id": 27,
            "class": "Text",
            "height": 33,
            "width": 80,
            "position": {
                "x1": 45,
                "y1": 218,
                "x2": 125,
                "y2": 251
            },
            "text_content": "Home",
            "negative_template": false,
            "is_custom": false,
            "is_vism": false
        },
        {
            "id": 28,
            "class": "Text",
            "height": 34,
            "width": 118,
            "position": {
                "x1": 404,
                "y1": 258,
                "x2": 522,
                "y2": 292
            },
            "text_content": " Upload",
            "parent": 6,
            "negative_template": false,
            "is_custom": false,
            "is_vism": false
        },
        {
            "id": 29,
            "class": "Text",
            "height": 28,
            "width": 130,
            "position": {
                "x1": 594,
                "y1": 260,
                "x2": 724,
                "y2": 288
            },
            "text_content": "+ Create v",
            "parent": 7,
            "negative_template": false,
            "is_custom": false,
            "is_vism": false
        },
        {
            "id": 30,
            "class": "Text",
            "height": 36,
            "width": 158,
            "position": {
                "x1": 804,
                "y1": 258,
                "x2": 962,
                "y2": 294
            },
            "text_content": " Organize v",
            "parent": 8,
            "negative_template": false,
            "is_custom": false,
            "is_vism": false
        },
        {
            "id": 31,
            "class": "Text",
            "height": 32,
            "width": 102,
            "position": {
                "x1": 1408,
                "y1": 260,
                "x2": 1510,
                "y2": 292
            },
            "text_content": " Share",
            "parent": 11,
            "negative_template": false,
            "is_custom": false,
            "is_vism": false
        },
        {
            "id": 32,
            "class": "Text",
            "height": 26,
            "width": 190,
            "position": {
                "x1": 1592,
                "y1": 262,
                "x2": 1782,
                "y2": 288
            },
            "text_content": "Only you have access",
            "negative_template": false,
            "is_custom": false,
            "is_vism": false
        },
        {
            "id": 33,
            "class": "Text",
            "height": 37,
            "width": 128,
            "position": {
                "x1": 13,
                "y1": 273,
                "x2": 141,
                "y2": 310
            },
            "text_content": "V All files",
            "negative_template": false,
            "is_custom": false,
            "is_vism": false
        },
        {
            "id": 34,
            "class": "Text",
            "height": 21,
            "width": 76,
            "position": {
                "x1": 104,
                "y1": 328,
                "x2": 180,
                "y2": 349
            },
            "text_content": "Content",
            "negative_template": false,
            "is_custom": false,
            "is_vism": false
        },
        {
            "id": 35,
            "class": "Text",
            "height": 38,
            "width": 88,
            "position": {
                "x1": 47,
                "y1": 380,
                "x2": 135,
                "y2": 418
            },
            "text_content": "Photos",
            "negative_template": false,
            "is_custom": false,
            "is_vism": false
        },
        {
            "id": 36,
            "class": "Text",
            "height": 27,
            "width": 126,
            "position": {
                "x1": 52,
                "y1": 447,
                "x2": 178,
                "y2": 474
            },
            "text_content": "Signatures",
            "negative_template": false,
            "is_custom": false,
            "is_vism": false
        },
        {
            "id": 37,
            "class": "Text",
            "height": 35,
            "width": 90,
            "position": {
                "x1": 49,
                "y1": 502,
                "x2": 139,
                "y2": 537
            },
            "text_content": "Shared",
            "negative_template": false,
            "is_custom": false,
            "is_vism": false
        },
        {
            "id": 38,
            "class": "Text",
            "height": 28,
            "width": 148,
            "position": {
                "x1": 52,
                "y1": 566,
                "x2": 200,
                "y2": 594
            },
            "text_content": "File requests",
            "negative_template": false,
            "is_custom": false,
            "is_vism": false
        },
        {
            "id": 39,
            "class": "Text",
            "height": 32,
            "width": 148,
            "position": {
                "x1": 50,
                "y1": 623,
                "x2": 198,
                "y2": 655
            },
            "text_content": "Deleted files",
            "negative_template": false,
            "is_custom": false,
            "is_vism": false
        },
        {
            "id": 40,
            "class": "Text",
            "height": 26,
            "width": 258,
            "position": {
                "x1": 948,
                "y1": 657,
                "x2": 1206,
                "y2": 683
            },
            "text_content": "Drop files here to upload,",
            "negative_template": false,
            "is_custom": false,
            "is_vism": false
        },
        {
            "id": 41,
            "class": "Text",
            "height": 26,
            "width": 260,
            "position": {
                "x1": 948,
                "y1": 693,
                "x2": 1208,
                "y2": 719
            },
            "text_content": "or use the 'Upload' button",
            "negative_template": false,
            "is_custom": false,
            "is_vism": false
        },
        {
            "id": 42,
            "class": "Text",
            "height": 26,
            "width": 270,
            "position": {
                "x1": 826,
                "y1": 844,
                "x2": 1096,
                "y2": 870
            },
            "text_content": "More ways to add content",
            "negative_template": false,
            "is_custom": false,
            "is_vism": false
        },
        {
            "id": 43,
            "class": "Text",
            "height": 22,
            "width": 150,
            "position": {
                "x1": 54,
                "y1": 881,
                "x2": 204,
                "y2": 903
            },
            "text_content": "Dropbox Basic",
            "negative_template": false,
            "is_custom": false,
            "is_vism": false
        },
        {
            "id": 44,
            "class": "Text",
            "height": 30,
            "width": 376,
            "position": {
                "x1": 884,
                "y1": 917,
                "x2": 1260,
                "y2": 947
            },
            "text_content": " Access this folder from your desktop",
            "parent": 18,
            "negative_template": false,
            "is_custom": false,
            "is_vism": false
        },
        {
            "id": 45,
            "class": "Text",
            "height": 28,
            "width": 222,
            "position": {
                "x1": 48,
                "y1": 933,
                "x2": 270,
                "y2": 961
            },
            "text_content": "0 bytes of 2 GB used O",
            "negative_template": false,
            "is_custom": false,
            "is_vism": false
        },
        {
            "id": 46,
            "class": "Text",
            "height": 25,
            "width": 304,
            "position": {
                "x1": 850,
                "y1": 1005,
                "x2": 1154,
                "y2": 1030
            },
            "text_content": " Import from Google Drive",
            "parent": 20,
            "negative_template": false,
            "is_custom": false,
            "is_vism": false
        },
        {
            "id": 47,
            "class": "Text",
            "height": 26,
            "width": 170,
            "position": {
                "x1": 52,
                "y1": 1022,
                "x2": 222,
                "y2": 1048
            },
            "text_content": "Privacy and legal",
            "negative_template": false,
            "is_custom": false,
            "is_vism": false
        }
    ],
    "img_shape": [
        1080,
        1920,
        3
    ],
    "raw_texts": ":::; Dropbox; Q Search; Upgrade; Dropbox / Content; E v; Home;  Upload; + Create v;  Organize v;  Share; Only you have access; V All files; Content; Photos; Signatures; Shared; File requests; Deleted files; Drop files here to upload,; or use the 'Upload' button; More ways to add content; Dropbox Basic;  Access this folder from your desktop; 0 bytes of 2 GB used O;  Import from Google Drive; Privacy and legal"
}